arcfutil/aff/__init__.py
arcfutil/aff/parser.py
arcfutil/aff/sorter.py
arcfutil/aff/easing/__init__.py
arcfutil/aff/easing/bezier.py
arcfutil/aff/easing/cheatsheet.py
arcfutil/aff/easing/easing_getter.py
arcfutil/aff/easing/simple_easings.py
arcfutil/aff/easing/slicer.py
arcfutil/aff/generator/__init__.py
arcfutil/aff/generator/arc_sample.py
arcfutil/aff/generator/timing_sample.py
arcfutil/aff/note/__init__.py
arcfutil/aff/note/arc.py
arcfutil/aff/note/camera.py
arcfutil/aff/note/common_note.py
arcfutil/aff/note/flick.py
arcfutil/aff/note/hold.py
arcfutil/aff/note/notegroup.py
arcfutil/aff/note/scenecontrol.py
arcfutil/aff/note/tap.py
arcfutil/aff/note/timing.py
arcfutil/aff/note/validstrings.py
arcfutil/cli/__init__.py
arcfutil/cli/arcade_clean.py
arcfutil/cli/cli.py
arcfutil/cli/songlist.py
arcfutil/cli/sortassets.py
arcfutil/exception/__init__.py
arcfutil-0.12.3.dist-info/licenses/LICENSE
arcfutil-0.12.3.dist-info/METADATA
arcfutil-0.12.3.dist-info/WHEEL
arcfutil-0.12.3.dist-info/entry_points.txt
arcfutil-0.12.3.dist-info/top_level.txt
arcfutil-0.12.3.dist-info/RECORD
