Metadata-Version: 2.4
Name: arcfutil
Version: 0.12.3
Summary: A Python module designed for processing Arcaea related files(.aff chart, songlist, etc.)
Home-page: https://github.com/feightwywx/arcfutil
Author: .direwolf
Author-email: kururinmiracle@outlook.com
Classifier: Programming Language :: Python :: 3
Classifier: License :: OSI Approved :: MIT License
Classifier: Operating System :: OS Independent
Requires-Python: >=3.4
License-File: LICENSE
Dynamic: author
Dynamic: author-email
Dynamic: classifier
Dynamic: description
Dynamic: description-content-type
Dynamic: home-page
Dynamic: license-file
Dynamic: requires-python
Dynamic: summary
